{"word":"厂","detail":[{"title":"基本字义解释","content":[[{"type":"text","content":"● "},{"type":"strong","content":"厂"},{"type":"strong","content":"（厰）"},{"type":"span","content":"chǎngㄔㄤˇ","class":["pinyin"]}],[{"type":"text","content":"◎ 指用机械制造生产资料或生活资料的工场。"}],[{"type":"text","content":"◎ 有空地方可以存货或进行加工的地方：煤"},{"type":"span","content":"厂","class":["fontred"]},{"type":"text","content":"。"}],[{"type":"text","content":"◎ 棚舍：“枳篱茅"},{"type":"span","content":"厂","class":["fontred"]},{"type":"text","content":"共桑麻。”"}],[{"type":"text","content":"◎ 中国明代为加强专制统治而设的特务机关。"}],[{"type":"text","content":"● "},{"type":"strong","content":"厂"},{"type":"span","content":"ānㄢˉ","class":["pinyin"]}],[{"type":"text","content":"◎ 同“"},{"type":"a","content":"庵"},{"type":"text","content":"”，多用于人名。"}],[{"type":"text","content":"● "},{"type":"strong","content":"厂"},{"type":"span","content":"hàn ㄏㄢˋ","class":["pinyin"]}],[{"type":"text","content":"◎ 山边岩石突出覆盖处，人可居住的地方。"}]]},{"title":"英文翻译","content":[[{"type":"text","content":"factory, workshop; radical 27"}]]},{"title":"详细字义解释","content":[[{"type":"text","content":"◎ "},{"type":"strong","content":"厂"},{"type":"text","content":" "},{"type":"span","content":"ān","class":["pinyin"]},{"type":"text","content":" "},{"type":"img","content":"","class":["sound"]},{"type":"text","content":" "}],[{"type":"span","content":"〈名词〉","class":["parts"]}],[{"type":"text","content":"(1) 同“庵”。多用于人名"}],[{"type":"text","content":"(2)  另见 "},{"type":"span","content":"chǎng","class":["pinyin"]},{"type":"text","content":" "},{"type":"img","content":"","class":["sound"]},{"type":"text","content":" "}]]},{"title":"基本词义解释","content":[[{"type":"text","content":"◎ "},{"type":"strong","content":"厂"},{"type":"text","content":" 廠、厰 "},{"type":"span","content":"chǎng","class":["pinyin"]},{"type":"text","content":" "},{"type":"img","content":"","class":["sound"]},{"type":"text","content":" "}],[{"type":"span","content":"〈名词〉","class":["parts"]}],[{"type":"text","content":"(1)  (形声。从广( "},{"type":"span","content":"yǎn","class":["pinyin"]},{"type":"text","content":"),敞声。从“广”,表示与房屋有关。本义:棚舍)"}],[{"type":"text","content":"(2)  没有墙壁的简易房屋"}],[{"type":"text","content":"(3)  又如:厂屋(棚舍;无隔墙的房屋)"}],[{"type":"text","content":"(4)  马屋;牲口棚子"},{"type":"br","content":""},{"type":"text","content":"架北墙为厂。——《齐民要术》"}],[{"type":"text","content":"(5)  工厂"},{"type":"br","content":""},{"type":"text","content":"正德十四年,广州置铁厂。——《明史·食货志》"}],[{"type":"text","content":"(6)  又如:纱厂;钢厂;面粉厂;纺织厂;造纸厂;木器厂"}],[{"type":"text","content":"(7)  明代的一种特务机构。如:厂臣(明东厂、西厂的主官);厂狱(指明代东厂、西厂囚禁犯人的牢狱)"}],[{"type":"text","content":"(8)  另见 "},{"type":"span","content":"ān","class":["pinyin"]},{"type":"text","content":" "},{"type":"img","content":"","class":["sound"]},{"type":"text","content":" "}]]},{"title":"常用词组","content":[[{"type":"text","content":"◎  "},{"type":"strong","content":"厂房"},{"type":"text","content":" "},{"type":"span","content":"chǎngfáng","class":["cpinyin"]}],[{"type":"text","content":"工厂的房屋,指车间"}],[{"type":"text","content":"◎  "},{"type":"strong","content":"厂规"},{"type":"text","content":" "},{"type":"span","content":"chǎngguī","class":["cpinyin"]}],[{"type":"text","content":"工厂的规章制度"}],[{"type":"text","content":"◎  "},{"type":"strong","content":"厂家"},{"type":"text","content":" "},{"type":"span","content":"chǎngjiā","class":["cpinyin"]}],[{"type":"text","content":"(1)工厂"},{"type":"br","content":""},{"type":"text","content":"(2)办工厂的人"}],[{"type":"text","content":"◎  "},{"type":"strong","content":"厂矿"},{"type":"text","content":" "},{"type":"span","content":"chǎngkuàng","class":["cpinyin"]}],[{"type":"text","content":"工厂和矿山"}],[{"type":"text","content":"◎  "},{"type":"strong","content":"厂商"},{"type":"text","content":" "},{"type":"span","content":"chǎngshāng","class":["cpinyin"]}],[{"type":"text","content":"(1)工厂和商店(多指私营的)"},{"type":"br","content":""},{"type":"text","content":"(2)开工厂的人"}],[{"type":"text","content":"◎  "},{"type":"strong","content":"厂史"},{"type":"text","content":" "},{"type":"span","content":"chǎngshǐ","class":["cpinyin"]}],[{"type":"text","content":"工厂的发展史"}],[{"type":"text","content":"◎  "},{"type":"strong","content":"厂休"},{"type":"text","content":" "},{"type":"span","content":"chǎngxiū","class":["cpinyin"]}],[{"type":"text","content":"工厂规定的职工休息日"},{"type":"br","content":""},{"type":"text","content":"我厂是每星期四厂休"}],[{"type":"text","content":"◎  "},{"type":"strong","content":"厂狱"},{"type":"text","content":" "},{"type":"span","content":"chǎngyù","class":["cpinyin"]}],[{"type":"text","content":"指明朝东厂(由太监掌管的特务机构)的监狱"},{"type":"br","content":""},{"type":"text","content":"及左公下厂狱。——清·方苞《左忠毅公逸事》"}],[{"type":"text","content":"◎  "},{"type":"strong","content":"厂长"},{"type":"text","content":" "},{"type":"span","content":"chǎngzhǎng","class":["cpinyin"]}],[{"type":"text","content":"负责全厂生产、生活和其他一切事务的领导人"}],[{"type":"text","content":"◎  "},{"type":"strong","content":"厂子"},{"type":"text","content":" "},{"type":"span","content":"chǎngzi","class":["cpinyin"]}],[{"type":"text","content":"[口]∶工厂"},{"type":"br","content":""},{"type":"text","content":"我们厂子新分来一个大学生"}]]},{"title":"康熙字典","content":[[{"type":"text","content":"【子集下】【厂字部】厂 ·康熙筆画：2　·部外筆画：0 "}],[{"type":"text","content":"【唐韻】呼旰切【集韻】虛旰切，"},{"type":"span","content":"𠀤"},{"type":"text","content":"音漢。【說文】山石之厓巖，人可居。象形。【集韻】籀作厈。【六書本義】厂，水厓高者。岸厈同。又【唐韻】呼旱切【集韻】許旱切，"},{"type":"span","content":"𠀤"},{"type":"text","content":"音"},{"type":"span","content":"䍐"},{"type":"text","content":"。義同。又【集韻】魚杴切，音嚴。"},{"type":"span","content":"䉷"},{"type":"text","content":"或省作厂。"}],[{"type":"text","content":"（廠）【廣韻】【正韻】昌兩切【集韻】【韻會】齒兩切，"},{"type":"span","content":"𠀤"},{"type":"text","content":"音敞。【廣韻】露舍也。【集韻】屋無壁也。　又【廣韻】【正韻】"},{"type":"span","content":"𠀤"},{"type":"text","content":"尺亮切。音唱。義同。"}]]},{"title":"说文解字","content":[[{"type":"text","content":"【卷九】【厂部】"},{"type":"span","content":"厂","class":["kszi"]}],[{"type":"text","content":"山石之厓巖，人可居。象形。凡厂之屬皆从厂。厈，籒文从干。呼旱切"}]]},{"title":"字源演变","content":[]},{"title":"同音字","content":[]}],"traditional":"廠","type":"通用字、常用字","pinyin":["chăng","hăn","ān"],"radical":"厂","stroke":"十画","total_stroke":"二画","stroke_order":"一ノ","input_method":{"bopomofo":"MH","number":"71200","unicode":"U+5382","wubi":"DGT"}}