{"word":"嗷","detail":[{"title":"基本字义解释","content":[[{"type":"text","content":"● "},{"type":"strong","content":"嗷"},{"type":"span","content":"áoㄠˊ","class":["pinyin"]}],[{"type":"text","content":"● "},{"type":"strong","content":"嗷"},{"type":"span","content":"áoㄠˊ","class":["pinyin"]}],[{"type":"text","content":"● "},{"type":"strong","content":"嗷"},{"type":"span","content":"áoㄠˊ","class":["pinyin"]}],[{"type":"text","content":"◎ 象声词，愁叹声，嘈杂声："},{"type":"span","content":"嗷嗷","class":["fontred"]},{"type":"text","content":"（哀号声）。"},{"type":"span","content":"嗷嗷","class":["fontred"]},{"type":"text","content":"待哺（形容饥饿时急于求食的样子）。"}],[{"type":"text","content":"◎ 象声词，愁叹声，嘈杂声："},{"type":"span","content":"嗷嗷","class":["fontred"]},{"type":"text","content":"（哀号声）。"},{"type":"span","content":"嗷嗷","class":["fontred"]},{"type":"text","content":"待哺（形容饥饿时急于求食的样子）。"}],[{"type":"text","content":"◎ 象声词，愁叹声，嘈杂声："},{"type":"span","content":"嗷嗷","class":["fontred"]},{"type":"text","content":"（哀号声）。"},{"type":"span","content":"嗷嗷","class":["fontred"]},{"type":"text","content":"待哺（形容饥饿时急于求食的样子）。"}],[{"type":"text","content":"◎ 象声词，愁叹声，嘈杂声："},{"type":"span","content":"嗷嗷","class":["fontred"]},{"type":"text","content":"（哀号声）。"},{"type":"span","content":"嗷嗷","class":["fontred"]},{"type":"text","content":"待哺（形容饥饿时急于求食的样子）。"}],[{"type":"text","content":"◎ 象声词，愁叹声，嘈杂声："},{"type":"span","content":"嗷嗷","class":["fontred"]},{"type":"text","content":"（哀号声）。"},{"type":"span","content":"嗷嗷","class":["fontred"]},{"type":"text","content":"待哺（形容饥饿时急于求食的样子）。"}]]},{"title":"英文翻译","content":[[{"type":"text","content":"loud clamor; sound of wailing"}]]},{"title":"详细字义解释","content":[[{"type":"text","content":"◎ "},{"type":"strong","content":"嗷"},{"type":"text","content":" "},{"type":"span","content":"áo","class":["pinyin"]},{"type":"text","content":" "},{"type":"img","content":"","class":["sound"]},{"type":"text","content":" "}],[{"type":"text","content":"◎ "},{"type":"strong","content":"嗷"},{"type":"text","content":" "},{"type":"span","content":"áo","class":["pinyin"]},{"type":"text","content":" "},{"type":"img","content":"","class":["sound"]},{"type":"text","content":" "}],[{"type":"text","content":"◎ "},{"type":"strong","content":"嗷"},{"type":"text","content":" "},{"type":"span","content":"áo","class":["pinyin"]},{"type":"text","content":" "},{"type":"img","content":"","class":["sound"]},{"type":"text","content":" "}],[{"type":"text","content":"◎ "},{"type":"strong","content":"嗷"},{"type":"text","content":" "},{"type":"span","content":"áo","class":["pinyin"]},{"type":"text","content":" "},{"type":"img","content":"","class":["sound"]},{"type":"text","content":" "}],[{"type":"text","content":"◎ "},{"type":"strong","content":"嗷"},{"type":"text","content":" "},{"type":"span","content":"áo","class":["pinyin"]},{"type":"text","content":" "},{"type":"img","content":"","class":["sound"]},{"type":"text","content":" "}],[{"type":"text","content":"◎ "},{"type":"strong","content":"嗷"},{"type":"text","content":" "},{"type":"span","content":"áo","class":["pinyin"]},{"type":"text","content":" "},{"type":"img","content":"","class":["sound"]},{"type":"text","content":" "}],[{"type":"text","content":"◎ "},{"type":"strong","content":"嗷"},{"type":"text","content":" "},{"type":"span","content":"áo","class":["pinyin"]},{"type":"text","content":" "},{"type":"img","content":"","class":["sound"]},{"type":"text","content":" "}],[{"type":"text","content":"<象>"}],[{"type":"text","content":"(1) (形声。从口,敖声。本义:哀鸣声)"}],[{"type":"text","content":"(2) 同本义"},{"type":"br","content":""},{"type":"text","content":"嗷,众口愁也。——《说文》"},{"type":"br","content":""},{"type":"text","content":"鸿雁于飞,哀鸣嗷嗷。——《诗·小雅·鸿雁》"}],[{"type":"text","content":"(2) 同本义"},{"type":"br","content":""},{"type":"text","content":"嗷,众口愁也。——《说文》"},{"type":"br","content":""},{"type":"text","content":"鸿雁于飞,哀鸣嗷嗷。——《诗·小雅·鸿雁》"}],[{"type":"text","content":"(2) 同本义"},{"type":"br","content":""},{"type":"text","content":"嗷,众口愁也。——《说文》"},{"type":"br","content":""},{"type":"text","content":"鸿雁于飞,哀鸣嗷嗷。——《诗·小雅·鸿雁》"}],[{"type":"text","content":"(2) 同本义"},{"type":"br","content":""},{"type":"text","content":"嗷,众口愁也。——《说文》"},{"type":"br","content":""},{"type":"text","content":"鸿雁于飞,哀鸣嗷嗷。——《诗·小雅·鸿雁》"}],[{"type":"text","content":"(2) 同本义"},{"type":"br","content":""},{"type":"text","content":"嗷,众口愁也。——《说文》"},{"type":"br","content":""},{"type":"text","content":"鸿雁于飞,哀鸣嗷嗷。——《诗·小雅·鸿雁》"}],[{"type":"text","content":"(3) 又如:嗷然(大喊大叫的样子)"}],[{"type":"text","content":"(4) 叫呼声;喧杂声"},{"type":"br","content":""},{"type":"text","content":"声嗸儗以寂寥兮。——《楚辞·惜贤》。注:“呼声也。”"},{"type":"br","content":""},{"type":"text","content":"谗口嗸嗸。——《汉书·刘向传》。注:“众声也。”"}],[{"type":"text","content":"(4) 叫呼声;喧杂声"},{"type":"br","content":""},{"type":"text","content":"声嗸儗以寂寥兮。——《楚辞·惜贤》。注:“呼声也。”"},{"type":"br","content":""},{"type":"text","content":"谗口嗸嗸。——《汉书·刘向传》。注:“众声也。”"}],[{"type":"text","content":"(4) 叫呼声;喧杂声"},{"type":"br","content":""},{"type":"text","content":"声嗸儗以寂寥兮。——《楚辞·惜贤》。注:“呼声也。”"},{"type":"br","content":""},{"type":"text","content":"谗口嗸嗸。——《汉书·刘向传》。注:“众声也。”"}],[{"type":"text","content":"(4) 叫呼声;喧杂声"},{"type":"br","content":""},{"type":"text","content":"声嗸儗以寂寥兮。——《楚辞·惜贤》。注:“呼声也。”"},{"type":"br","content":""},{"type":"text","content":"谗口嗸嗸。——《汉书·刘向传》。注:“众声也。”"}],[{"type":"text","content":"(4) 叫呼声;喧杂声"},{"type":"br","content":""},{"type":"text","content":"声嗸儗以寂寥兮。——《楚辞·惜贤》。注:“呼声也。”"},{"type":"br","content":""},{"type":"text","content":"谗口嗸嗸。——《汉书·刘向传》。注:“众声也。”"}],[{"type":"text","content":"(5) 又如:嗷嘈(吵闹);嗷骚(喧扰,不平静)"}]]},{"title":"常用词组","content":[[{"type":"text","content":"◎  "},{"type":"strong","content":"嗷嗷待哺"},{"type":"text","content":" "},{"type":"span","content":"áo’áo-dàibǔ","class":["cpinyin"]}],[{"type":"text","content":"◎  "},{"type":"strong","content":"嗷嗷待哺"},{"type":"text","content":" "},{"type":"span","content":"áo’áo-dàibǔ","class":["cpinyin"]}],[{"type":"text","content":"◎  "},{"type":"strong","content":"嗷嗷待哺"},{"type":"text","content":" "},{"type":"span","content":"áo’áo-dàibǔ","class":["cpinyin"]}],[{"type":"text","content":"◎  "},{"type":"strong","content":"嗷嗷待哺"},{"type":"text","content":" "},{"type":"span","content":"áo’áo-dàibǔ","class":["cpinyin"]}],[{"type":"text","content":"嗷嗷:哀号声;待:等待;哺:哺育,喂养。原意指小鸟饥饿时叫着要东西吃的样子。后常用以形容饥民渴求得食而急待解救的悲惨情景"},{"type":"br","content":""},{"type":"text","content":"可奈满城无粮,嗷嗷待哺。——蔡东藩《唐史演义》"}],[{"type":"text","content":"嗷嗷:哀号声;待:等待;哺:哺育,喂养。原意指小鸟饥饿时叫着要东西吃的样子。后常用以形容饥民渴求得食而急待解救的悲惨情景"},{"type":"br","content":""},{"type":"text","content":"可奈满城无粮,嗷嗷待哺。——蔡东藩《唐史演义》"}],[{"type":"text","content":"嗷嗷:哀号声;待:等待;哺:哺育,喂养。原意指小鸟饥饿时叫着要东西吃的样子。后常用以形容饥民渴求得食而急待解救的悲惨情景"},{"type":"br","content":""},{"type":"text","content":"可奈满城无粮,嗷嗷待哺。——蔡东藩《唐史演义》"}]]},{"title":"康熙字典","content":[[{"type":"text","content":"【丑集上】【口字部】嗷 ·康熙筆画：14　·部外筆画：11 "}],[{"type":"text","content":"【唐韻】五牢切【集韻】【韻會】【正韻】牛刀切，"},{"type":"span","content":"𠀤"},{"type":"text","content":"音敖。【說文】本作嗷，衆口愁也。　又【西京雜記】紛紜翔集，嘈嗷鳴啼。　【玉篇】作嗸。【韻會】通作囂敖謷熬。嗷字从口"},{"type":"span","content":"𢾕"},{"type":"text","content":"聲。"}],[{"type":"text","content":"【唐韻】五牢切【集韻】【韻會】【正韻】牛刀切，"},{"type":"span","content":"𠀤"},{"type":"text","content":"音敖。【說文】本作嗷，衆口愁也。　又【西京雜記】紛紜翔集，嘈嗷鳴啼。　【玉篇】作嗸。【韻會】通作囂敖謷熬。嗷字从口"},{"type":"span","content":"𢾕"},{"type":"text","content":"聲。"}],[{"type":"text","content":"【唐韻】五牢切【集韻】【韻會】【正韻】牛刀切，"},{"type":"span","content":"𠀤"},{"type":"text","content":"音敖。【說文】本作嗷，衆口愁也。　又【西京雜記】紛紜翔集，嘈嗷鳴啼。　【玉篇】作嗸。【韻會】通作囂敖謷熬。嗷字从口"},{"type":"span","content":"𢾕"},{"type":"text","content":"聲。"}],[{"type":"text","content":"【唐韻】五牢切【集韻】【韻會】【正韻】牛刀切，"},{"type":"span","content":"𠀤"},{"type":"text","content":"音敖。【說文】本作嗷，衆口愁也。　又【西京雜記】紛紜翔集，嘈嗷鳴啼。　【玉篇】作嗸。【韻會】通作囂敖謷熬。嗷字从口"},{"type":"span","content":"𢾕"},{"type":"text","content":"聲。"}],[{"type":"text","content":"【唐韻】五牢切【集韻】【韻會】【正韻】牛刀切，"},{"type":"span","content":"𠀤"},{"type":"text","content":"音敖。【說文】本作嗷，衆口愁也。　又【西京雜記】紛紜翔集，嘈嗷鳴啼。　【玉篇】作嗸。【韻會】通作囂敖謷熬。嗷字从口"},{"type":"span","content":"𢾕"},{"type":"text","content":"聲。"}]]},{"title":"说文解字","content":[[{"type":"text","content":"【卷二】【口部】"},{"type":"span","content":"嗷","class":["kszi"]}],[{"type":"text","content":"【卷二】【口部】"},{"type":"span","content":"嗷","class":["kszi"]}],[{"type":"text","content":"眾口愁也。从口敖聲。《詩》曰：“哀鳴嗷嗷。”五牢切"}]]},{"title":"字源演变","content":[]},{"title":"同音字","content":[]}],"type":"通用字","pinyin":["áo"],"radical":"口","stroke":"十画","total_stroke":"十三画","t_radical":"口","t_stroke":"十一画","t_total_stroke":"十四画","stroke_order":"丨フ一一一丨一フノノ一ノ丶","input_method":{"bopomofo":"RGSK","number":"68040","unicode":"U+55F7","wubi":"KGQT"}}