{"word":"捱","detail":[{"title":"基本字义解释","content":[[{"type":"text","content":"● "},{"type":"strong","content":"捱"},{"type":"span","content":"áiㄞˊ","class":["pinyin"]}],[{"type":"text","content":"◎ 同“"},{"type":"a","content":"挨"},{"type":"text","content":"（"},{"type":"span","content":"ái","class":["pinyin"]},{"type":"text","content":"）”。"}]]},{"title":"英文翻译","content":[[{"type":"text","content":"put off, procrastinate; endure"}]]},{"title":"康熙字典","content":[[{"type":"text","content":"【卯集中】【手字部】捱 ·康熙筆画：12　·部外筆画：8 "}],[{"type":"text","content":"【集韻】宜佳切，音厓。拒也。　又俗謂延緩曰捱。"}]]},{"title":"字源演变","content":[]},{"title":"同音字","content":[]}],"type":"生僻字","pinyin":["ái","āi"],"radical":"扌","stroke":"八画","total_stroke":"十一画","t_radical":"手","t_stroke":"八画","t_total_stroke":"十一画","stroke_order":"一丨一一ノ一丨一一丨一","input_method":{"bopomofo":"QMGG","number":"51014","unicode":"U+6371","wubi":"RDFF"}}